cryojax/__init__.py
cryojax/_config.py
cryojax/_internal.py
cryojax/cryojax_version.py
cryojax/atom_util/__init__.py
cryojax/atom_util/_element_utils.py
cryojax/atom_util/_geometry.py
cryojax/constants/__init__.py
cryojax/constants/_conventions.py
cryojax/constants/_physical_constants.py
cryojax/constants/_scattering_factor_parameters.py
cryojax/coordinates/__init__.py
cryojax/dataset/__init__.py
cryojax/dataset/_dataset.py
cryojax/dataset/_particle_data/__init__.py
cryojax/dataset/_particle_data/base_particle_dataset.py
cryojax/dataset/_particle_data/particle_simulation.py
cryojax/dataset/_particle_data/relion.py
cryojax/experimental/__init__.py
cryojax/io/__init__.py
cryojax/io/_mrc.py
cryojax/io/_pdb.py
cryojax/io/_starfile.py
cryojax/io/pdb_names.xml
cryojax/jax_util/__init__.py
cryojax/jax_util/_batched_loop.py
cryojax/jax_util/_errors.py
cryojax/jax_util/_filter_specs.py
cryojax/jax_util/_linear_operator.py
cryojax/jax_util/_pytree_transforms.py
cryojax/jax_util/_typing.py
cryojax/jax_util/_grid_search/__init__.py
cryojax/jax_util/_grid_search/custom_types.py
cryojax/jax_util/_grid_search/pytree_manipulation.py
cryojax/jax_util/_grid_search/search_loop.py
cryojax/jax_util/_grid_search/search_method.py
cryojax/ndimage/__init__.py
cryojax/ndimage/_downsample.py
cryojax/ndimage/_edges.py
cryojax/ndimage/_fft.py
cryojax/ndimage/_fourier_statistics.py
cryojax/ndimage/_fourier_utils.py
cryojax/ndimage/_map_coordinates.py
cryojax/ndimage/_normalize.py
cryojax/ndimage/_radial_average.py
cryojax/ndimage/_rescale_pixel_size.py
cryojax/ndimage/_coordinates/__init__.py
cryojax/ndimage/_coordinates/_geometry.py
cryojax/ndimage/_coordinates/_make_coordinate_grids.py
cryojax/ndimage/_operators/__init__.py
cryojax/ndimage/_operators/_fourier_operator.py
cryojax/ndimage/_operators/_real_operator.py
cryojax/ndimage/_transforms/__init__.py
cryojax/ndimage/_transforms/_base_transform.py
cryojax/ndimage/_transforms/_filters.py
cryojax/ndimage/_transforms/_masks.py
cryojax-0.5.5.dist-info/METADATA
cryojax-0.5.5.dist-info/WHEEL
cryojax-0.5.5.dist-info/licenses/LICENSE
cryojax-0.5.5.dist-info/RECORD
