Metadata-Version: 2.4
Name: cryojax
Version: 0.5.5
Summary: Cryo-EM image simulation and analysis powered by JAX
Project-URL: repository, https://github.com/michael-0brien/cryojax
Author-email: Michael O'Brien <michaelobrien@g.harvard.edu>
License:                   GNU LESSER GENERAL PUBLIC LICENSE
License-File: LICENSE
Keywords: cryo-EM,electron-microscopy,equinox,jax
Classifier: Development Status :: 4 - Beta
Classifier: Intended Audience :: Developers
Classifier: Intended Audience :: Science/Research
Classifier: License :: OSI Approved :: GNU Lesser General Public License v2 (LGPLv2)
Classifier: Operating System :: OS Independent
Classifier: Programming Language :: Python
Classifier: Programming Language :: Python :: 3
Requires-Python: >=3.10
Requires-Dist: equinox>=0.11.0
Requires-Dist: jax
Requires-Dist: jaxtyping>=0.2.23
Requires-Dist: lineax
Requires-Dist: mdtraj
Requires-Dist: mmdf
Requires-Dist: mrcfile
Requires-Dist: pandas
Requires-Dist: starfile
Requires-Dist: typing-extensions>=4.5.0
Provides-Extra: dev
Requires-Dist: pre-commit; extra == 'dev'
Provides-Extra: docs
Requires-Dist: griffe==1.7.3; extra == 'docs'
Requires-Dist: hippogriffe==0.2.2; extra == 'docs'
Requires-Dist: mkdocs-include-exclude-files==0.1.0; extra == 'docs'
Requires-Dist: mkdocs-ipynb==0.1.1; extra == 'docs'
Requires-Dist: mkdocs-material==9.6.7; extra == 'docs'
Requires-Dist: mkdocs==1.6.1; extra == 'docs'
Requires-Dist: mkdocstrings-python==1.16.8; extra == 'docs'
Requires-Dist: mkdocstrings==0.28.3; extra == 'docs'
Requires-Dist: pymdown-extensions==10.14.3; extra == 'docs'
Requires-Dist: ruff; extra == 'docs'
Provides-Extra: extras
Requires-Dist: jax-finufft>=1.2.0; extra == 'extras'
Provides-Extra: tests
Requires-Dist: pycistem==0.4.1; (sys_platform == 'linux' and python_version < '3.12') and extra == 'tests'
Requires-Dist: pytest; extra == 'tests'
Requires-Dist: pytest-cov; extra == 'tests'
Requires-Dist: typeguard==2.13.3; extra == 'tests'
